__init__.py
data_gempa/__init__.py
data_gempa/main.py
Gempa-0.0.1.dist-info/LICENSE
Gempa-0.0.1.dist-info/METADATA
Gempa-0.0.1.dist-info/WHEEL
Gempa-0.0.1.dist-info/top_level.txt
Gempa-0.0.1.dist-info/RECORD
